rl_algo_impls/benchmark_publish.py
rl_algo_impls/compare_runs.py
rl_algo_impls/enjoy.py
rl_algo_impls/huggingface_publish.py
rl_algo_impls/optimize.py
rl_algo_impls/selfplay_enjoy.py
rl_algo_impls/train.py
rl_algo_impls/a2c/a2c.py
rl_algo_impls/a2c/optimize.py
rl_algo_impls/dqn/dqn.py
rl_algo_impls/dqn/policy.py
rl_algo_impls/dqn/q_net.py
rl_algo_impls/hyperparams/a2c.yml
rl_algo_impls/hyperparams/dqn.yml
rl_algo_impls/hyperparams/ppo.yml
rl_algo_impls/hyperparams/vpg.yml
rl_algo_impls/lux/agent.py
rl_algo_impls/lux/kit/cargo.py
rl_algo_impls/lux/kit/config.py
rl_algo_impls/lux/kit/factory.py
rl_algo_impls/lux/kit/forward_sim.py
rl_algo_impls/lux/kit/kit.py
rl_algo_impls/lux/kit/team.py
rl_algo_impls/lux/kit/unit.py
rl_algo_impls/lux/kit/utils.py
rl_algo_impls/ppo/ppo.py
rl_algo_impls/publish/markdown_format.py
rl_algo_impls/runner/config.py
rl_algo_impls/runner/evaluate.py
rl_algo_impls/runner/running_utils.py
rl_algo_impls/runner/selfplay_evaluate.py
rl_algo_impls/runner/train.py
rl_algo_impls/runner/wandb_load.py
rl_algo_impls/shared/algorithm.py
rl_algo_impls/shared/gae.py
rl_algo_impls/shared/schedule.py
rl_algo_impls/shared/stats.py
rl_algo_impls/shared/trajectory.py
rl_algo_impls/shared/actor/__init__.py
rl_algo_impls/shared/actor/actor.py
rl_algo_impls/shared/actor/categorical.py
rl_algo_impls/shared/actor/gaussian.py
rl_algo_impls/shared/actor/gridnet.py
rl_algo_impls/shared/actor/gridnet_decoder.py
rl_algo_impls/shared/actor/make_actor.py
rl_algo_impls/shared/actor/multi_discrete.py
rl_algo_impls/shared/actor/state_dependent_noise.py
rl_algo_impls/shared/callbacks/__init__.py
rl_algo_impls/shared/callbacks/callback.py
rl_algo_impls/shared/callbacks/eval_callback.py
rl_algo_impls/shared/callbacks/lux_hyperparam_transitions.py
rl_algo_impls/shared/callbacks/optimize_callback.py
rl_algo_impls/shared/callbacks/reward_decay_callback.py
rl_algo_impls/shared/callbacks/self_play_callback.py
rl_algo_impls/shared/encoder/__init__.py
rl_algo_impls-0.0.13.dist-info/LICENSE
rl_algo_impls-0.0.13.dist-info/METADATA
rl_algo_impls-0.0.13.dist-info/WHEEL
rl_algo_impls-0.0.13.dist-info/top_level.txt
rl_algo_impls-0.0.13.dist-info/RECORD
