Metadata-Version: 2.1
Name: rl-algo-impls
Version: 0.0.13
Summary: Implementations of reinforcement learning algorithms
Author-email: Scott Goodfriend <goodfriend.scott@gmail.com>
License: MIT License
Project-URL: Homepage, https://github.com/sgoodfriend/rl-algo-impls
Classifier: License :: OSI Approved :: MIT License
Classifier: Development Status :: 3 - Alpha
Classifier: Programming Language :: Python :: 3.7
Classifier: Programming Language :: Python :: 3.8
Classifier: Programming Language :: Python :: 3.9
Classifier: Programming Language :: Python :: 3.10
Requires-Python: >=3.7
License-File: LICENSE
Requires-Dist: cmake
Requires-Dist: swig
Requires-Dist: scipy
Requires-Dist: torch
Requires-Dist: torchvision
Requires-Dist: tensorboard (<2.12,>=2.11.2)
Requires-Dist: AutoROM.accept-rom-license (<0.5,>=0.4.2)
Requires-Dist: stable-baselines3[extra] (<1.8,>=1.7.0)
Requires-Dist: gym[box2d] (<0.22,>=0.21.0)
Requires-Dist: pyglet (==1.5.27)
Requires-Dist: wandb (==0.13.10)
Requires-Dist: pyvirtualdisplay
Requires-Dist: pybullet
Requires-Dist: tabulate
Requires-Dist: huggingface-hub
Requires-Dist: optuna
Requires-Dist: dash
Requires-Dist: kaleido
Requires-Dist: PyYAML
Requires-Dist: scikit-learn
Provides-Extra: all
Requires-Dist: rl-algo-impls[test] ; extra == 'all'
Requires-Dist: rl-algo-impls[procgen] ; extra == 'all'
Requires-Dist: rl-algo-impls[microrts] ; extra == 'all'
Requires-Dist: rl-algo-impls[lux] ; extra == 'all'
Provides-Extra: jupyter
Requires-Dist: jupyter ; extra == 'jupyter'
Requires-Dist: notebook ; extra == 'jupyter'
Provides-Extra: lux
Requires-Dist: luxai-s2 ; extra == 'lux'
Requires-Dist: juxai-s2 ; extra == 'lux'
Provides-Extra: microrts
Requires-Dist: gym-microrts ; extra == 'microrts'
Provides-Extra: microrts-paper
Requires-Dist: numpy (<1.24.0) ; extra == 'microrts-paper'
Requires-Dist: gym-microrts (==0.3.2) ; extra == 'microrts-paper'
Provides-Extra: microrts-ppo
Requires-Dist: numpy (<1.24.0) ; extra == 'microrts-ppo'
Requires-Dist: gym-microrts (==0.2.0) ; extra == 'microrts-ppo'
Provides-Extra: procgen
Requires-Dist: numexpr (>=2.8.4) ; extra == 'procgen'
Requires-Dist: gym3 ; extra == 'procgen'
Requires-Dist: glfw (<1.13,>=1.12.0) ; extra == 'procgen'
Requires-Dist: procgen ; (platform_machine == "x86_64") and extra == 'procgen'
Provides-Extra: test
Requires-Dist: pytest ; extra == 'test'
Requires-Dist: black ; extra == 'test'
Requires-Dist: mypy ; extra == 'test'
Requires-Dist: flake8 ; extra == 'test'
Requires-Dist: flake8-bugbear ; extra == 'test'
Requires-Dist: isort ; extra == 'test'
